pykit/__init__.py
pykit/check.py
pykit/cls.py
pykit/code.py
pykit/condition.py
pykit/crypto.py
pykit/d.py
pykit/dt.py
pykit/env.py
pykit/err.py
pykit/err_utils.py
pykit/expectation.py
pykit/fmt.py
pykit/func.py
pykit/history.py
pykit/keeper.py
pykit/lock.py
pykit/log.py
pykit/mark.py
pykit/never.py
pykit/obj.py
pykit/path.py
pykit/proc.py
pykit/ptr.py
pykit/query.py
pykit/rand.py
pykit/range.py
pykit/ref.py
pykit/res.py
pykit/singleton.py
pykit/str.py
pykit/subproc.py
pykit/t.py
pykit/tb.py
pykit/thd.py
pykit/trait.py
pykit/tree.py
pykit/types.py
pykit/uuid.py
sb_pykit-0.12.3.dist-info/LICENSE
sb_pykit-0.12.3.dist-info/METADATA
sb_pykit-0.12.3.dist-info/WHEEL
sb_pykit-0.12.3.dist-info/RECORD
